XLXml/__init__.py
XLXml/converter.py
xltoxml_conv-1.0.0.dist-info/METADATA
xltoxml_conv-1.0.0.dist-info/WHEEL
xltoxml_conv-1.0.0.dist-info/top_level.txt
xltoxml_conv-1.0.0.dist-info/RECORD
