Metadata-Version: 2.1
Name: xltoxml_conv
Version: 1.0.0
Summary: Convert Excel files to XML format
Requires-Dist: openpyxl
